LICENSE
README.md
pyproject.toml
src/spectrum_image/__init__.py
src/spectrum_image.egg-info/PKG-INFO
src/spectrum_image.egg-info/SOURCES.txt
src/spectrum_image.egg-info/dependency_links.txt
src/spectrum_image.egg-info/requires.txt
src/spectrum_image.egg-info/top_level.txt
src/spectrum_image/EELS/EELS_LP.py
src/spectrum_image/EELS/EELS_SI.py
src/spectrum_image/EELS/EELS_bgsub.py
src/spectrum_image/EELS/EELS_edge.py
src/spectrum_image/EELS/EELS_lineshapes.py
src/spectrum_image/EELS/EELS_util.py
src/spectrum_image/EELS/__init__.py
src/spectrum_image/RIXS/RIXS_EM.py
src/spectrum_image/RIXS/__init__.py