Metadata-Version: 2.1
Name: spectrum_image
Version: 0.3.1
Summary: Python Package for EELS (Electron Energy Loss Spectroscopy) Analysis
Author-email: Suk Hyun Sung <sukhsung@umich.edu>, Michale Colletta <mrc297@cornell.edu>, Alex Stangle <astangel@umich.edu>
Project-URL: Homepage, https://github.com/sukhsung/spectrum-image
Project-URL: Repository, https://github.com/sukhsung/spectrum-image
Project-URL: Bug Tracker, https://github.com/sukhsung/spectrum-image/issues
Keywords: Electron Microscopy,EELS,TEM,STEM,Electron Energy Loss Spectroscopy
Classifier: Development Status :: 3 - Alpha
Classifier: Programming Language :: Python
Requires-Python: >=3.10
License-File: LICENSE
Requires-Dist: numpy
Requires-Dist: matplotlib
Requires-Dist: jupyterlab
Requires-Dist: ipympl
Requires-Dist: scipy
Requires-Dist: tqdm
Requires-Dist: lmfit
